LICENSE
MANIFEST.in
README.md
package.json
setup.py
dongjak_dash_mantine_components/Accordion.py
dongjak_dash_mantine_components/AccordionControl.py
dongjak_dash_mantine_components/AccordionItem.py
dongjak_dash_mantine_components/AccordionPanel.py
dongjak_dash_mantine_components/ActionIcon.py
dongjak_dash_mantine_components/ActionIconGroup.py
dongjak_dash_mantine_components/Affix.py
dongjak_dash_mantine_components/Alert.py
dongjak_dash_mantine_components/Anchor.py
dongjak_dash_mantine_components/AppShell.py
dongjak_dash_mantine_components/AppShellAside.py
dongjak_dash_mantine_components/AppShellFooter.py
dongjak_dash_mantine_components/AppShellHeader.py
dongjak_dash_mantine_components/AppShellMain.py
dongjak_dash_mantine_components/AppShellNavbar.py
dongjak_dash_mantine_components/AppShellSection.py
dongjak_dash_mantine_components/AreaChart.py
dongjak_dash_mantine_components/AspectRatio.py
dongjak_dash_mantine_components/Autocomplete.py
dongjak_dash_mantine_components/Avatar.py
dongjak_dash_mantine_components/AvatarGroup.py
dongjak_dash_mantine_components/BackgroundImage.py
dongjak_dash_mantine_components/Badge.py
dongjak_dash_mantine_components/BarChart.py
dongjak_dash_mantine_components/Blockquote.py
dongjak_dash_mantine_components/Box.py
dongjak_dash_mantine_components/Breadcrumbs.py
dongjak_dash_mantine_components/Burger.py
dongjak_dash_mantine_components/Button.py
dongjak_dash_mantine_components/ButtonGroup.py
dongjak_dash_mantine_components/Card.py
dongjak_dash_mantine_components/CardSection.py
dongjak_dash_mantine_components/Carousel.py
dongjak_dash_mantine_components/CarouselSlide.py
dongjak_dash_mantine_components/Center.py
dongjak_dash_mantine_components/Checkbox.py
dongjak_dash_mantine_components/CheckboxGroup.py
dongjak_dash_mantine_components/Chip.py
dongjak_dash_mantine_components/ChipGroup.py
dongjak_dash_mantine_components/Code.py
dongjak_dash_mantine_components/CodeHighlight.py
dongjak_dash_mantine_components/CodeHighlightTabs.py
dongjak_dash_mantine_components.egg-info/PKG-INFO
dongjak_dash_mantine_components.egg-info/SOURCES.txt
dongjak_dash_mantine_components.egg-info/dependency_links.txt
dongjak_dash_mantine_components.egg-info/top_level.txt