Metadata-Version: 2.1
Name: dongjak_dash_mantine_components
Version: 0.14.3
Summary: Plotly Dash Components based on Mantine
Home-page: https://github.com/cruldra/dash-mantine-components
Author: Snehil Vijay <snehilvj@outlook.com>
Author-email: snehilvj@outlook.com
License: MIT
Classifier: Framework :: Dash
Classifier: Framework :: Flask
License-File: LICENSE
